{"elapsed_ms": 34175, "mode": "paid_beta_rc", "ready": false, "steps": [{"elapsed_ms": 12576, "name": "cargo_workspace_tests", "reason": "", "status": "pass"}, {"elapsed_ms": 9755, "name": "backend_launch_gate", "reason": "backend_launch_gate_commerce_local_env_missing", "status": "external_secret_missing"}, {"elapsed_ms": 115, "name": "local_signoff", "reason": "local_signoff_prerequisites_unsatisfied", "status": "external_secret_missing"}, {"elapsed_ms": 74, "name": "ses_readiness", "reason": "credentialed_ses_identity_missing", "status": "external_secret_missing"}, {"elapsed_ms": 25, "name": "staging_billing_rehearsal", "reason": "credentialed_billing_month_missing", "status": "live_evidence_gap"}, {"elapsed_ms": 368, "name": "browser_preflight", "reason": "browser_preflight_env_gap", "status": "external_secret_missing"}, {"elapsed_ms": 35, "name": "browser_auth_setup", "reason": "browser_auth_setup_env_gap", "status": "external_secret_missing"}, {"elapsed_ms": 5241, "name": "terraform_static_guardrails", "reason": "", "status": "pass"}, {"elapsed_ms": 27, "name": "staging_runtime_smoke", "reason": "credentialed_staging_smoke_inputs_missing", "status": "live_evidence_gap"}, {"elapsed_ms": 256, "name": "admin_broadcast", "reason": "", "status": "pass"}, {"elapsed_ms": 706, "name": "billing_health_last_activity", "reason": "", "status": "pass"}, {"elapsed_ms": 454, "name": "audit_timeline", "reason": "", "status": "pass"}, {"elapsed_ms": 259, "name": "status_runtime", "reason": "", "status": "pass"}, {"elapsed_ms": 110, "name": "ses_inbound", "reason": "credentialed_ses_inbound_inputs_missing", "status": "external_secret_missing"}, {"elapsed_ms": 702, "name": "canary_customer_loop", "reason": "probe_env_gap_aws_inbox_env_missing", "status": "skip"}, {"elapsed_ms": 422, "name": "canary_outside_aws", "reason": "", "status": "pass"}, {"elapsed_ms": 1012, "name": "stripe_webhook_signature_matrix_idempotency", "reason": "", "status": "pass"}, {"elapsed_ms": 27, "name": "test_clock", "reason": "stripe_test_clock_full_cycle_owner_requires_live_mode", "status": "live_evidence_gap"}, {"elapsed_ms": 244, "name": "tenant_isolation", "reason": "", "status": "pass"}, {"elapsed_ms": 866, "name": "signup_abuse", "reason": "", "status": "pass"}, {"elapsed_ms": 26, "name": "browser_signup_paid", "reason": "critical_surface_skipped", "status": "fail"}, {"elapsed_ms": 25, "name": "browser_portal_cancel", "reason": "critical_surface_skipped", "status": "fail"}], "timestamp": "2026-06-04T13:52:07Z", "verdict": "fail"}
