{"gates": [{"checks_run": 6, "duration_ms": 3256, "name": "reliability", "reason": "", "status": "pass"}, {"checks_run": 5, "duration_ms": 1923, "name": "security", "reason": "", "status": "pass"}, {"checks_run": 6, "duration_ms": 624, "name": "commerce", "reason": "check_stripe_webhook_forwarding, check_usage_records_populated, check_rollup_current", "status": "fail"}, {"checks_run": 1, "duration_ms": 493, "name": "load", "reason": "", "status": "pass"}, {"checks_run": 1, "duration_ms": 19, "name": "ci_cd", "reason": "", "status": "pass"}], "timestamp": "2026-05-02T04:38:22Z", "verdict": "fail"}
